{
  "id": "llama-4-maverick",
  "name": "Llama 4 Maverick",
  "provider": "meta",
  "status": null,
  "previous_model_id": null,
  "description": null,
  "announced_date": null,
  "release_date": "2025-04-05T00:00:00",
  "deprecation_date": "",
  "retirement_date": null,
  "input_context_length": 1048576,
  "output_context_length": 1048576,
  "license": null,
  "multimodal": true,
  "input_types": "text,image",
  "output_types": "text",
  "web_access": null,
  "reasoning": null,
  "fine_tunable": null,
  "knowledge_cutoff": null,
  "api_reference_link": null,
  "playground_link": null,
  "paper_link": null,
  "announcement_link": null,
  "repository_link": null,
  "weights_link": null,
  "parameter_count": null,
  "training_tokens": null,
  "benchmark_results": [
    {
      "benchmark_id": "arc-agi-2",
      "score": "0.00%",
      "is_self_reported": false,
      "other_info": null,
      "source_link": "https://arcprize.org/leaderboard"
    },
    {
      "benchmark_id": "arc-agi-1",
      "score": "4.40%",
      "is_self_reported": false,
      "other_info": null,
      "source_link": "https://arcprize.org/leaderboard"
    },
    {
      "benchmark_id": "gpqa-diamond",
      "score": "69.80%",
      "is_self_reported": true,
      "other_info": null,
      "source_link": "https://ai.meta.com/blog/llama-4-multimodal-intelligence/"
    },
    {
      "benchmark_id": "simplebench",
      "score": "27.70%",
      "is_self_reported": false,
      "other_info": null,
      "source_link": "https://simple-bench.com/index.html"
    },
    {
      "benchmark_id": "confabulations",
      "score": 22.58,
      "is_self_reported": false,
      "other_info": null,
      "source_link": "https://github.com/lechmazur/confabulations"
    },
    {
      "benchmark_id": "thematic-generalisation",
      "score": 2.04,
      "is_self_reported": false,
      "other_info": null,
      "source_link": "https://github.com/lechmazur/generalization"
    },
    {
      "benchmark_id": "nyt-connections",
      "score": "19.10%",
      "is_self_reported": false,
      "other_info": null,
      "source_link": "https://github.com/lechmazur/nyt-connections"
    },
    {
      "benchmark_id": "elimination-game",
      "score": 4.78,
      "is_self_reported": false,
      "other_info": null,
      "source_link": "https://github.com/lechmazur/elimination_game"
    },
    {
      "benchmark_id": "ai2-sciarena",
      "score": 872.73,
      "is_self_reported": false,
      "other_info": null,
      "source_link": "https://sciarena.allen.ai/"
    }
  ],
  "prices": [
    {
      "api_provider": null,
      "input_token_price": "0.00000017",
      "cached_input_token_price": null,
      "output_token_price": "0.00000085",
      "throughput": "",
      "latency": "",
      "source_link": null,
      "other_info": null
    }
  ]
}